Metadata-Version: 2.1
Name: polypython
Version: 0.0.0.0.3
Summary: Analysis of Raman spectral images for plastic content.
Home-page: https://github.com/JLevermore/polypython
Author: Joseph M Levermore
Author-email: j.levermore@imperial.ac.uk
License: MIT
Platform: UNKNOWN
Classifier: Development Status :: 5 - Production/Stable
Classifier: Intended Audience :: Science/Research
Classifier: Programming Language :: Python :: 3
Classifier: License :: OSI Approved :: MIT License
Classifier: Operating System :: OS Independent
Requires-Python: >=3.6
